loklak.py
setup.cfg
setup.py
bin/loklak
python_loklak_api.egg-info/PKG-INFO
python_loklak_api.egg-info/SOURCES.txt
python_loklak_api.egg-info/dependency_links.txt
python_loklak_api.egg-info/not-zip-safe
python_loklak_api.egg-info/requires.txt
python_loklak_api.egg-info/top_level.txt