Metadata-Version: 1.1
Name: python-loklak-api
Version: 1.6
Summary: Python API for loklak, Anonymous distributed P2P Systems.
Home-page: https://github.com/loklak/loklak_api_python
Author: Sudheesh Singanamalla
Author-email: sudheesh95@gmail.com
License: UNKNOWN
Download-URL: https://github.com/loklak/loklak_api_python
Keywords: Twitter Loklak Anonymous API
Platform: Linux/Mac
Classifier: Development Status :: 3 - Alpha
Classifier: Intended Audience :: Developers
Classifier: Programming Language :: Python
Classifier: Programming Language :: Python :: 2
Classifier: Programming Language :: Python :: 3
Classifier: Topic :: Internet
